LICENSE
MANIFEST.in
README.md
pyproject.toml
setup.cfg
setup.py
src/polymer_property_prediction/__init__.py
src/polymer_property_prediction/molecule.py
src/polymer_property_prediction/polymer_properties_from_smiles.py
src/polymer_property_prediction.egg-info/PKG-INFO
src/polymer_property_prediction.egg-info/SOURCES.txt
src/polymer_property_prediction.egg-info/dependency_links.txt
src/polymer_property_prediction.egg-info/requires.txt
src/polymer_property_prediction.egg-info/top_level.txt