Metadata-Version: 2.1
Name: polymer-property-prediction
Version: 1.0.11
Summary: Library to calculate the physical properties of molecules based on their SMILES representations
Home-page: https://github.com/IBM/polymer_property_prediction
Author: flowdisc@br.ibm.com
Author-email: flowdisc@br.ibm.com
License: BSD 3-Clause License
Platform: UNKNOWN
Classifier: Programming Language :: Python :: 3
Classifier: Operating System :: OS Independent
Classifier: License :: OSI Approved :: BSD License
Requires-Python: >=3.10
License-File: LICENSE
